hidpi_tk/__init__.py
hidpi_tk/__init__.pyi
hidpi_tk/py.typed
hidpi_tk/.ruff_cache/.gitignore
hidpi_tk/.ruff_cache/CACHEDIR.TAG
hidpi_tk/.ruff_cache/0.11.12/471334828925074570
hidpi_tk-1.3.0.dist-info/licenses/LICENSE
hidpi_tk-1.3.0.dist-info/METADATA
hidpi_tk-1.3.0.dist-info/WHEEL
hidpi_tk-1.3.0.dist-info/top_level.txt
hidpi_tk-1.3.0.dist-info/RECORD
