Metadata-Version: 2.4
Name: hidpi-tk
Version: 1.3.0
Summary: Fixed Tkinter-based GUI window blurry on high-DPI monitors.
Author-email: Wulian233 <xiguawulian@gmail.com>
License-Expression: Apache-2.0
Project-URL: Repository, https://github.com/Wulian233/hidpi-tk.git
Project-URL: GitHub, https://github.com/Wulian233/hidpi-tk
Project-URL: Bug Tracker, https://github.com/Wulian233/hidpi-tk/issues
Project-URL: Changelog, https://github.com/Wulian233/hidpi-tk/blob/main/CHANGES.rst
Keywords: hidpi-tk,tkinter,dpi,highdpi,blurry,tkdpi
Classifier: Development Status :: 5 - Production/Stable
Classifier: Programming Language :: Python
Classifier: Programming Language :: Python :: 3
Classifier: Operating System :: Microsoft :: Windows
Classifier: Topic :: Software Development :: Libraries
Requires-Python: >=3.6
License-File: LICENSE
Dynamic: license-file
